{
  "lastUpdated": "2026-06-11T11:23:46.592Z",
  "rates": {
    "malaria": {
      "annualDeaths": 609930,
      "year": 2024,
      "source": "WHO GHO MALARIA_EST_DEATHS (2024)"
    },
    "cholera": {
      "annualDeaths": 675533,
      "year": 2024,
      "source": "WHO GHO WHS3_62 (2024)"
    },
    "hiv-aids": {
      "annualDeaths": 630000,
      "year": 2024,
      "source": "UNAIDS 2024 (AIDS-related deaths)"
    },
    "covid-19": {
      "annualDeaths": 80000,
      "year": 2026,
      "source": "WHO estimate 2026"
    },
    "hantavirus": {
      "annualDeaths": 200,
      "year": 2026,
      "source": "CDC/WHO 2026"
    }
  }
}